{
  "project_info": {
    "project_number": "644335414212",
    "firebase_url": "https://taler-db.firebaseio.com",
    "project_id": "taler-db",
    "storage_bucket": "taler-db.appspot.com"
  },
  "client": [
    {
      "client_info": {
        "mobilesdk_app_id": "1:644335414212:android:e9cb6ca1babbbfb6fad291",
        "android_client_info": {
          "package_name": "com.example.taler"
        }
      },
      "oauth_client": [
        {
          "client_id": "644335414212-vu6nofh1mimqoev6qp5tj4e9slfkepro.apps.googleusercontent.com",
          "client_type": 1,
          "android_info": {
            "package_name": "com.example.taler",
            "certificate_hash": "27a12a10c000faa3aa8ff6d67412f911cdaa6edb"
          }
        },
        {
          "client_id": "644335414212-2p2khm3qr3r1fvbnq6fs3pnhkcp74b33.apps.googleusercontent.com",
          "client_type": 1,
          "android_info": {
            "package_name": "com.example.taler",
            "certificate_hash": "c93f1d83a6b25e64626f1c4506c165d9ad8f65c7"
          }
        },
        {
          "client_id": "644335414212-8acdurmukqdj6ptftvoae0hom6ugvm06.apps.googleusercontent.com",
          "client_type": 3
        }
      ],
      "api_key": [
        {
          "current_key": "AIzaSyDJJReSnvXxggPSJlem7qFPrNYNYjVqsSQ"
        }
      ],
      "services": {
        "appinvite_service": {
          "other_platform_oauth_client": [
            {
              "client_id": "644335414212-8acdurmukqdj6ptftvoae0hom6ugvm06.apps.googleusercontent.com",
              "client_type": 3
            }
          ]
        }
      }
    }
  ],
  "configuration_version": "1"
}